{
  "$schema": "https://raw.githubusercontent.com/OpenLightingProject/open-fixture-library/master/schemas/fixture.json",
  "name": "Dynamo Scan LED",
  "categories": ["Scanner"],
  "meta": {
    "authors": ["Brioche"],
    "createDate": "2023-06-06",
    "lastModifyDate": "2023-06-06",
    "importPlugin": {
      "plugin": "qlcplus_4.12.1",
      "date": "2023-06-06",
      "comment": "created by Q Light Controller Plus (version 4.12.7)"
    }
  },
  "physical": {
    "dimensions": [361, 187, 216],
    "weight": 3.96,
    "power": 35,
    "DMXconnector": "3-pin",
    "bulb": {
      "type": "LED"
    },
    "lens": {
      "degreesMinMax": [15, 15]
    }
  },
  "wheels": {
    "Color wheel": {
      "slots": [
        {
          "type": "Color",
          "name": "White"
        },
        {
          "type": "Color",
          "name": "White & Purplle"
        },
        {
          "type": "Color",
          "name": "Purple"
        },
        {
          "type": "Color",
          "name": "Purple & Green"
        },
        {
          "type": "Color",
          "name": "Green"
        },
        {
          "type": "Color",
          "name": "Green & Light blue"
        },
        {
          "type": "Color",
          "name": "Light blue"
        },
        {
          "type": "Color",
          "name": "Light blue & Pink"
        },
        {
          "type": "Color",
          "name": "Pink"
        },
        {
          "type": "Color",
          "name": "Pink & Deep blue"
        },
        {
          "type": "Color",
          "name": "Deep blue"
        },
        {
          "type": "Color",
          "name": "Deep blue & Yellow"
        },
        {
          "type": "Color",
          "name": "Yellow"
        },
        {
          "type": "Color",
          "name": "Yellow & Orange"
        },
        {
          "type": "Color",
          "name": "Orange"
        },
        {
          "type": "Color",
          "name": "Orange & White"
        }
      ]
    },
    "Gobo wheel": {
      "slots": [
        {
          "type": "Gobo",
          "name": "No fonction"
        },
        {
          "type": "Gobo",
          "name": "Gobo 1"
        },
        {
          "type": "Gobo",
          "name": "Gobo 2"
        },
        {
          "type": "Gobo",
          "name": "Gobo 3"
        },
        {
          "type": "Gobo",
          "name": "Gobo 4"
        },
        {
          "type": "Gobo",
          "name": "Gobo 5"
        },
        {
          "type": "Gobo",
          "name": "Gobo 6"
        },
        {
          "type": "Gobo",
          "name": "Gobo 7"
        },
        {
          "type": "Gobo",
          "name": "Gobo 1 + Shake slow to fast"
        },
        {
          "type": "Gobo",
          "name": "Gobo 2 + Shake slow to fast"
        },
        {
          "type": "Gobo",
          "name": "Gobo 3 + Shake slow to fast"
        },
        {
          "type": "Gobo",
          "name": "Gobo 4 + Shake slow to fast"
        },
        {
          "type": "Gobo",
          "name": "Gobo 5 + Shake slow to fast"
        },
        {
          "type": "Gobo",
          "name": "Gobo 6 + Shake slow to fast"
        },
        {
          "type": "Gobo",
          "name": "Gobo 7 + Shake slow to fast"
        },
        {
          "type": "Gobo",
          "name": "No fonction"
        }
      ]
    }
  },
  "availableChannels": {
    "Strobe": {
      "defaultValue": 0,
      "capabilities": [
        {
          "dmxRange": [0, 7],
          "type": "ShutterStrobe",
          "shutterEffect": "Strobe",
          "speedStart": "slow",
          "speedEnd": "fast"
        },
        {
          "dmxRange": [8, 255],
          "type": "StrobeSpeed",
          "speedStart": "slow",
          "speedEnd": "fast",
          "comment": "Strobe (Slow to fast)"
        }
      ]
    },
    "Dimmer": {
      "defaultValue": 0,
      "capability": {
        "type": "Intensity"
      }
    },
    "Pan": {
      "defaultValue": 0,
      "capability": {
        "type": "Pan",
        "angleStart": "0deg",
        "angleEnd": "170deg"
      }
    },
    "Tilt": {
      "defaultValue": 0,
      "capability": {
        "type": "Tilt",
        "angleStart": "0deg",
        "angleEnd": "80deg"
      }
    },
    "Pan/Tilt speed": {
      "defaultValue": 0,
      "capability": {
        "type": "PanTiltSpeed",
        "speedStart": "slow",
        "speedEnd": "fast"
      }
    },
    "Color wheel": {
      "defaultValue": 0,
      "capabilities": [
        {
          "dmxRange": [0, 7],
          "type": "WheelSlot",
          "slotNumber": 1,
          "comment": "White"
        },
        {
          "dmxRange": [8, 15],
          "type": "WheelSlot",
          "slotNumber": 2,
          "comment": "White & Purplle"
        },
        {
          "dmxRange": [16, 23],
          "type": "WheelSlot",
          "slotNumber": 3,
          "comment": "Purple"
        },
        {
          "dmxRange": [24, 31],
          "type": "WheelSlot",
          "slotNumber": 4,
          "comment": "Purple & Green"
        },
        {
          "dmxRange": [32, 39],
          "type": "WheelSlot",
          "slotNumber": 5,
          "comment": "Green"
        },
        {
          "dmxRange": [40, 47],
          "type": "WheelSlot",
          "slotNumber": 6,
          "comment": "Green & Light blue"
        },
        {
          "dmxRange": [48, 55],
          "type": "WheelSlot",
          "slotNumber": 7,
          "comment": "Light blue"
        },
        {
          "dmxRange": [56, 63],
          "type": "WheelSlot",
          "slotNumber": 8,
          "comment": "Light blue & Pink"
        },
        {
          "dmxRange": [64, 71],
          "type": "WheelSlot",
          "slotNumber": 9,
          "comment": "Pink"
        },
        {
          "dmxRange": [72, 79],
          "type": "WheelSlot",
          "slotNumber": 10,
          "comment": "Pink & Deep blue"
        },
        {
          "dmxRange": [80, 87],
          "type": "WheelSlot",
          "slotNumber": 11,
          "comment": "Deep blue"
        },
        {
          "dmxRange": [88, 95],
          "type": "WheelSlot",
          "slotNumber": 12,
          "comment": "Deep blue & Yellow"
        },
        {
          "dmxRange": [96, 103],
          "type": "WheelSlot",
          "slotNumber": 13,
          "comment": "Yellow"
        },
        {
          "dmxRange": [104, 111],
          "type": "WheelSlot",
          "slotNumber": 14,
          "comment": "Yellow & Orange"
        },
        {
          "dmxRange": [112, 119],
          "type": "WheelSlot",
          "slotNumber": 15,
          "comment": "Orange"
        },
        {
          "dmxRange": [120, 127],
          "type": "WheelSlot",
          "slotNumber": 16,
          "comment": "Orange & White"
        },
        {
          "dmxRange": [128, 191],
          "type": "WheelSlot",
          "slotNumber": 17,
          "comment": "Color Wheel rotation forward (Slow -> Fast rotation)"
        },
        {
          "dmxRange": [192, 255],
          "type": "WheelSlot",
          "slotNumber": 18,
          "comment": "Color Wheel rotation backward (Slow -> Fast rotation)"
        }
      ]
    },
    "Gobo wheel": {
      "defaultValue": 0,
      "capabilities": [
        {
          "dmxRange": [0, 7],
          "type": "WheelSlot",
          "slotNumber": 1,
          "comment": "No fonction"
        },
        {
          "dmxRange": [8, 15],
          "type": "WheelSlot",
          "slotNumber": 2,
          "comment": "Gobo 1"
        },
        {
          "dmxRange": [16, 23],
          "type": "WheelSlot",
          "slotNumber": 3,
          "comment": "Gobo 2"
        },
        {
          "dmxRange": [24, 31],
          "type": "WheelSlot",
          "slotNumber": 4,
          "comment": "Gobo 3"
        },
        {
          "dmxRange": [32, 39],
          "type": "WheelSlot",
          "slotNumber": 5,
          "comment": "Gobo 4"
        },
        {
          "dmxRange": [40, 47],
          "type": "WheelSlot",
          "slotNumber": 6,
          "comment": "Gobo 5"
        },
        {
          "dmxRange": [48, 55],
          "type": "WheelSlot",
          "slotNumber": 7,
          "comment": "Gobo 6"
        },
        {
          "dmxRange": [56, 63],
          "type": "WheelSlot",
          "slotNumber": 8,
          "comment": "Gobo 7"
        },
        {
          "dmxRange": [64, 71],
          "type": "WheelShake",
          "slotNumber": 9,
          "shakeSpeedStart": "slow",
          "shakeSpeedEnd": "fast",
          "comment": "Gobo 1 + Shake"
        },
        {
          "dmxRange": [72, 79],
          "type": "WheelShake",
          "slotNumber": 10,
          "shakeSpeedStart": "slow",
          "shakeSpeedEnd": "fast",
          "comment": "Gobo 2 + Shake"
        },
        {
          "dmxRange": [80, 87],
          "type": "WheelShake",
          "slotNumber": 11,
          "shakeSpeedStart": "slow",
          "shakeSpeedEnd": "fast",
          "comment": "Gobo 3 + Shake"
        },
        {
          "dmxRange": [88, 95],
          "type": "WheelShake",
          "slotNumber": 12,
          "shakeSpeedStart": "slow",
          "shakeSpeedEnd": "fast",
          "comment": "Gobo 4 + Shake"
        },
        {
          "dmxRange": [96, 103],
          "type": "WheelShake",
          "slotNumber": 13,
          "shakeSpeedStart": "slow",
          "shakeSpeedEnd": "fast",
          "comment": "Gobo 5 + Shake"
        },
        {
          "dmxRange": [104, 111],
          "type": "WheelShake",
          "slotNumber": 14,
          "shakeSpeedStart": "slow",
          "shakeSpeedEnd": "fast",
          "comment": "Gobo 6 + Shake"
        },
        {
          "dmxRange": [112, 119],
          "type": "WheelShake",
          "slotNumber": 15,
          "shakeSpeedStart": "slow",
          "shakeSpeedEnd": "fast",
          "comment": "Gobo 7 + Shake"
        },
        {
          "dmxRange": [120, 127],
          "type": "WheelSlot",
          "slotNumber": 16,
          "comment": "No fonction"
        },
        {
          "dmxRange": [128, 191],
          "type": "WheelSlot",
          "slotNumber": 17,
          "comment": "Gobo wheel Rotation forward (slow -> fast rotation)"
        },
        {
          "dmxRange": [192, 255],
          "type": "WheelSlot",
          "slotNumber": 18,
          "comment": "Gobo wheel Rotation backward (slow -> fast rotation)"
        }
      ]
    },
    "Control modes": {
      "defaultValue": 0,
      "capabilities": [
        {
          "dmxRange": [0, 2],
          "type": "NoFunction"
        },
        {
          "dmxRange": [3, 84],
          "type": "NoFunction"
        },
        {
          "dmxRange": [85, 169],
          "type": "NoFunction"
        },
        {
          "dmxRange": [170, 255],
          "type": "NoFunction"
        }
      ]
    },
    "Reset": {
      "defaultValue": 0,
      "capabilities": [
        {
          "dmxRange": [0, 254],
          "type": "NoFunction"
        },
        {
          "dmxRange": [255, 255],
          "type": "Maintenance",
          "comment": "System reset"
        }
      ]
    }
  },
  "modes": [
    {
      "name": "Normal",
      "channels": [
        "Strobe",
        "Dimmer",
        "Pan",
        "Tilt",
        "Pan/Tilt speed",
        "Color wheel",
        "Gobo wheel",
        "Control modes",
        "Reset"
      ]
    }
  ]
}
