{
  "$schema": "https://raw.githubusercontent.com/OpenLightingProject/open-fixture-library/master/schemas/fixture.json",
  "name": "Frezno Fresnel",
  "categories": ["Other"],
  "meta": {
    "authors": ["Anonymous"],
    "createDate": "2025-08-02",
    "lastModifyDate": "2025-08-02"
  },
  "links": {
    "manual": [
      "https://acousticlighting.com/product/silverstar-frezno-series/"
    ]
  },
  "availableChannels": {
    "Dimmer": {
      "defaultValue": "0%",
      "capability": {
        "type": "Intensity"
      }
    },
    "Red": {
      "defaultValue": "100%",
      "capability": {
        "type": "ColorIntensity",
        "color": "Red"
      }
    },
    "Green": {
      "defaultValue": "100%",
      "capability": {
        "type": "ColorIntensity",
        "color": "Green"
      }
    },
    "Blue": {
      "defaultValue": "100%",
      "capability": {
        "type": "ColorIntensity",
        "color": "Blue"
      }
    },
    "Amber": {
      "defaultValue": "100%",
      "capability": {
        "type": "ColorIntensity",
        "color": "Amber"
      }
    },
    "Lime": {
      "defaultValue": 0,
      "capability": {
        "type": "ColorIntensity",
        "color": "Lime"
      }
    },
    "Strobe": {
      "defaultValue": "0%",
      "capability": {
        "type": "ShutterStrobe",
        "shutterEffect": "Open"
      }
    },
    "Zoom": {
      "defaultValue": "50%",
      "capability": {
        "type": "Zoom",
        "angleStart": "narrow",
        "angleEnd": "wide"
      }
    },
    "Reserved": {
      "defaultValue": "0%",
      "capability": {
        "type": "NoFunction"
      }
    }
  },
  "modes": [
    {
      "name": "SSP",
      "channels": [
        "Dimmer",
        "Red",
        "Green",
        "Blue",
        "Amber",
        "Lime",
        "Strobe",
        "Zoom",
        "Reserved"
      ]
    }
  ]
}
